[
    {
        "key": "dbln",
        "value": "%7B%2261555067162048%22%3A%22GlbCkVld%22%7D",
        "domain": "facebook.com",
        "path": "/login/device-based/",
        "hostOnly": false,
        "creation": "2025-04-22T12:01:09.348Z",
        "lastAccessed": "2025-04-22T12:01:09.349Z"
    },
    {
        "key": "sb",
        "value": "52X7Z_4kR3K5jctbmp2B8DJE",
        "domain": "facebook.com",
        "path": "/",
        "hostOnly": false,
        "creation": "2025-04-22T12:01:09.349Z",
        "lastAccessed": "2025-04-22T12:01:09.349Z"
    },
    {
        "key": "locale",
        "value": "vi_VN",
        "domain": "facebook.com",
        "path": "/",
        "hostOnly": false,
        "creation": "2025-04-22T12:01:09.349Z",
        "lastAccessed": "2025-04-22T12:01:09.349Z"
    },
    {
        "key": "ps_l",
        "value": "1",
        "domain": "facebook.com",
        "path": "/",
        "hostOnly": false,
        "creation": "2025-04-22T12:01:09.349Z",
        "lastAccessed": "2025-04-22T12:01:09.349Z"
    },
    {
        "key": "ps_n",
        "value": "1",
        "domain": "facebook.com",
        "path": "/",
        "hostOnly": false,
        "creation": "2025-04-22T12:01:09.349Z",
        "lastAccessed": "2025-04-22T12:01:09.349Z"
    },
    {
        "key": "dpr",
        "value": "1.100000023841858",
        "domain": "facebook.com",
        "path": "/",
        "hostOnly": false,
        "creation": "2025-04-22T12:01:09.349Z",
        "lastAccessed": "2025-04-22T12:01:09.349Z"
    },
    {
        "key": "datr",
        "value": "N7QEaPE5JA2NoLJa5Hvn6S6X",
        "domain": "facebook.com",
        "path": "/",
        "hostOnly": false,
        "creation": "2025-04-22T12:01:09.349Z",
        "lastAccessed": "2025-04-22T12:01:09.349Z"
    },
    {
        "key": "c_user",
        "value": "61555067162048",
        "domain": "facebook.com",
        "path": "/",
        "hostOnly": false,
        "creation": "2025-04-22T12:01:09.349Z",
        "lastAccessed": "2025-04-22T12:01:09.349Z"
    },
    {
        "key": "wd",
        "value": "1745x866",
        "domain": "facebook.com",
        "path": "/",
        "hostOnly": false,
        "creation": "2025-04-22T12:01:09.349Z",
        "lastAccessed": "2025-04-22T12:01:09.349Z"
    },
    {
        "key": "fr",
        "value": "1tirrwRlo4zFVkHJG.AWe7T9XuTDwGT1vuApo2aYNi2WOdNaGUCA8Y42xWMBkM_pSXgTg.BoB4St..AAA.0.0.BoB4St.AWebmLe9ImDQ2lnZijhS7bzUALc",
        "domain": "facebook.com",
        "path": "/",
        "hostOnly": false,
        "creation": "2025-04-22T12:01:09.349Z",
        "lastAccessed": "2025-04-22T12:01:09.349Z"
    },
    {
        "key": "xs",
        "value": "33%3ARNAsLIneE29JdQ%3A2%3A1745143474%3A-1%3A6284%3A%3AAcXZxUi1F2TH5_Tlp2AYeoXSMlKMQnsx21okSpX8wA",
        "domain": "facebook.com",
        "path": "/",
        "hostOnly": false,
        "creation": "2025-04-22T12:01:09.349Z",
        "lastAccessed": "2025-04-22T12:01:09.349Z"
    },
    {
        "key": "presence",
        "value": "C%7B%22t3%22%3A%5B%5D%2C%22utc3%22%3A1745323183410%2C%22v%22%3A1%7D",
        "domain": "facebook.com",
        "path": "/",
        "hostOnly": false,
        "creation": "2025-04-22T12:01:09.349Z",
        "lastAccessed": "2025-04-22T12:01:09.349Z"
    }
]
